[{"id":"133009","channel":"СТВ Казахстан","link":"https://sc.id-tv.kz/STV.m3u8?checkedby:iptvcat.com","country":"kazakhstan","liveliness":"70","status":"online","lastChecked":"2021-01-28T00:00:00Z","format":"sd","mbps":"1509, ...","URI":["asia","kazakhstan","kazakhstan_"]},{"id":"133011","channel":"Хабар 24","link":"https://live-24kz.cdnvideo.ru/24kz/24kz.sdp/playlist.m3u8?checkedby:iptvcat.com","country":"kazakhstan","liveliness":"93","status":"online","lastChecked":"2021-01-29T00:00:00Z","format":"fhd 2k","mbps":"8378","URI":["asia","kazakhstan","kazakhstan_"]},{"id":"56014","channel":"KZ | MTRK, MTRK","link":"https://tvcdn01.oktv.kz/tv/mtrk/tracks-v1a1/mono.m3u8?checkedby:iptvcat.com","country":"kazakhstan","liveliness":"98","status":"online","lastChecked":"2021-01-28T00:00:00Z","format":"sd","mbps":"1509","URI":["asia","kazakhstan","kazakhstan_"]},{"id":"56002","channel":"KZ | Мir +3, Мir +3","link":"https://sc.id-tv.kz/Mir_38_39.m3u8?checkedby:iptvcat.com","country":"kazakhstan","liveliness":"87","status":"online","lastChecked":"2021-01-29T00:00:00Z","format":"sd","mbps":"1706","URI":["asia","kazakhstan","kazakhstan_"]},{"id":"133002","channel":"ID Fashion (KZ)","link":"https://sc.id-tv.kz/IDFashion.m3u8?checkedby:iptvcat.com","country":"kazakhstan","liveliness":"74","status":"online","lastChecked":"2021-01-29T00:00:00Z","format":"sd","mbps":"1706, ...","URI":["asia","kazakhstan","kazakhstan_"]},{"id":"56005","channel":"Dombyra TV, KZ | Dombyra TV","link":"https://sc.id-tv.kz/Dombyra_38_39.m3u8?checkedby:iptvcat.com","country":"kazakhstan","liveliness":"84","status":"online","lastChecked":"2021-01-29T00:00:00Z","format":"sd","mbps":"2334","URI":["asia","kazakhstan","kazakhstan_"]},{"id":"132996","channel":"Almaty TV","link":"https://live-almatytv.cdnvideo.ru/almatytv/almatytv.sdp/playlist.m3u8?checkedby:iptvcat.com","country":"kazakhstan","liveliness":"99","status":"online","lastChecked":"2021-01-29T00:00:00Z","format":"hd","mbps":"5020","URI":["asia","kazakhstan","kazakhstan_"]},{"id":"132998","channel":"Astana TV","link":"https://sc.id-tv.kz/Astana.m3u8?checkedby:iptvcat.com","country":"kazakhstan","liveliness":"61","status":"online","lastChecked":"2021-01-29T00:00:00Z","format":"sd","mbps":"1706, ...","URI":["asia","kazakhstan","kazakhstan_"]},{"id":"56004","channel":"Asyl Arna, KZ | Asyl Arna","link":"https://sc.id-tv.kz/AsylArna_38_39.m3u8?checkedby:iptvcat.com","country":"kazakhstan","liveliness":"93","status":"online","lastChecked":"2021-01-29T00:00:00Z","format":"sd","mbps":"1019","URI":["asia","kazakhstan","kazakhstan_"]},{"id":"132999","channel":"Atameken Business","link":"https://live-atameken.cdnvideo.ru/atameken/atameken_hq.sdp/playlist.m3u8?checkedby:iptvcat.com","country":"kazakhstan","liveliness":"96","status":"online","lastChecked":"2021-01-28T00:00:00Z","format":"hd","mbps":"3625","URI":["asia","kazakhstan","kazakhstan_"]},{"id":"56000","channel":"1 Kanal Evraziya, KZ | 1 Kanal Evraziya","link":"https://sc.id-tv.kz/1KanalEvraziya_38_39.m3u8?checkedby:iptvcat.com","country":"kazakhstan","liveliness":"81","status":"online","lastChecked":"2021-01-28T00:00:00Z","format":"sd","mbps":"1019","URI":["asia","kazakhstan","kazakhstan_"]},{"id":"132996","channel":"Almaty TV","link":"https://live-almatytv.cdnvideo.ru/almatytv/almatytv.sdp/playlist.m3u8?checkedby:iptvcat.com","country":"kazakhstan","liveliness":"99","status":"online","lastChecked":"2021-01-29T00:00:00Z","format":"hd","mbps":"5020","URI":["asia","kazakhstan","kazakhstan_"]},{"id":"132998","channel":"Astana TV","link":"https://sc.id-tv.kz/Astana.m3u8?checkedby:iptvcat.com","country":"kazakhstan","liveliness":"61","status":"online","lastChecked":"2021-01-29T00:00:00Z","format":"sd","mbps":"1706, ...","URI":["asia","kazakhstan","kazakhstan_"]},{"id":"56004","channel":"Asyl Arna, KZ | Asyl Arna","link":"https://sc.id-tv.kz/AsylArna_38_39.m3u8?checkedby:iptvcat.com","country":"kazakhstan","liveliness":"93","status":"online","lastChecked":"2021-01-29T00:00:00Z","format":"sd","mbps":"1019","URI":["asia","kazakhstan","kazakhstan_"]},{"id":"132999","channel":"Atameken Business","link":"https://live-atameken.cdnvideo.ru/atameken/atameken_hq.sdp/playlist.m3u8?checkedby:iptvcat.com","country":"kazakhstan","liveliness":"96","status":"online","lastChecked":"2021-01-28T00:00:00Z","format":"hd","mbps":"3625","URI":["asia","kazakhstan","kazakhstan_"]},{"id":"133009","channel":"СТВ Казахстан","link":"https://sc.id-tv.kz/STV.m3u8?checkedby:iptvcat.com","country":"kazakhstan","liveliness":"70","status":"online","lastChecked":"2021-01-28T00:00:00Z","format":"sd","mbps":"1509, ...","URI":["asia","kazakhstan","kazakhstan_"]},{"id":"133011","channel":"Хабар 24","link":"https://live-24kz.cdnvideo.ru/24kz/24kz.sdp/playlist.m3u8?checkedby:iptvcat.com","country":"kazakhstan","liveliness":"93","status":"online","lastChecked":"2021-01-29T00:00:00Z","format":"fhd 2k","mbps":"8378","URI":["asia","kazakhstan","kazakhstan_"]},{"id":"56000","channel":"1 Kanal Evraziya, KZ | 1 Kanal Evraziya","link":"https://sc.id-tv.kz/1KanalEvraziya_38_39.m3u8?checkedby:iptvcat.com","country":"kazakhstan","liveliness":"81","status":"online","lastChecked":"2021-01-28T00:00:00Z","format":"sd","mbps":"1019","URI":["asia","kazakhstan","kazakhstan_"]},{"id":"1781","channel":"Almaty TV, Almaty TV (KZ)","link":"http://live-almatytv.cdnvideo.ru/almatytv/almatytv.sdp/playlist.m3u8?checkedby:iptvcat.com","country":"kazakhstan","liveliness":"99","status":"online","lastChecked":"2021-01-28T00:00:00Z","format":"hd","mbps":"5020","URI":["europe","russian_federation_-_","kazakhstan","russian_federation","kazakhstan_"]},{"id":"13898","channel":"Astana TV, Astana TV (KZ)","link":"https://sc.id-tv.kz/Astana_38_39.m3u8?checkedby:iptvcat.com","country":"kazakhstan","liveliness":"80","status":"online","lastChecked":"2021-01-29T00:00:00Z","format":"sd","mbps":"1019","URI":["europe","russian_federation_-_","kazakhstan","russian_federation","kazakhstan_"]},{"id":"1781","channel":"Almaty TV, Almaty TV (KZ)","link":"http://live-almatytv.cdnvideo.ru/almatytv/almatytv.sdp/playlist.m3u8?checkedby:iptvcat.com","country":"kazakhstan","liveliness":"99","status":"online","lastChecked":"2021-01-28T00:00:00Z","format":"hd","mbps":"5020","URI":["europe","russian_federation_-_","kazakhstan","russian_federation","kazakhstan_"]},{"id":"13898","channel":"Astana TV, Astana TV (KZ)","link":"https://sc.id-tv.kz/Astana_38_39.m3u8?checkedby:iptvcat.com","country":"kazakhstan","liveliness":"80","status":"online","lastChecked":"2021-01-29T00:00:00Z","format":"sd","mbps":"1019","URI":["europe","russian_federation_-_","kazakhstan","russian_federation","kazakhstan_"]},{"id":"1781","channel":"Almaty TV, Almaty TV (KZ)","link":"http://live-almatytv.cdnvideo.ru/almatytv/almatytv.sdp/playlist.m3u8?checkedby:iptvcat.com","country":"kazakhstan","liveliness":"99","status":"online","lastChecked":"2021-01-28T00:00:00Z","format":"hd","mbps":"5020","URI":["europe","russian_federation_-_","kazakhstan","russian_federation","kazakhstan_"]},{"id":"13898","channel":"Astana TV, Astana TV (KZ)","link":"https://sc.id-tv.kz/Astana_38_39.m3u8?checkedby:iptvcat.com","country":"kazakhstan","liveliness":"80","status":"online","lastChecked":"2021-01-29T00:00:00Z","format":"sd","mbps":"1019","URI":["europe","russian_federation_-_","kazakhstan","russian_federation","kazakhstan_"]},{"id":"56000","channel":"1 Kanal Evraziya, KZ | 1 Kanal Evraziya","link":"https://sc.id-tv.kz/1KanalEvraziya_38_39.m3u8?checkedby:iptvcat.com","country":"kazakhstan","liveliness":"81","status":"online","lastChecked":"2021-01-28T00:00:00Z","format":"sd","mbps":"1019","URI":["asia","kazakhstan","kazakhstan_"]},{"id":"13896","channel":"31 канал","link":"https://sc.id-tv.kz/31Kanal_38_39.m3u8?checkedby:iptvcat.com","country":"kazakhstan","liveliness":"84","status":"online","lastChecked":"2021-01-29T00:00:00Z","format":"sd","mbps":"1706","URI":["kazakhstan","kazakhstan_"]},{"id":"13897","channel":"7 канал (KZ)","link":"https://sc.id-tv.kz/7_kanal_38_39.m3u8?checkedby:iptvcat.com","country":"kazakhstan","liveliness":"86","status":"online","lastChecked":"2021-01-29T00:00:00Z","format":"sd","mbps":"1019","URI":["kazakhstan","kazakhstan_"]},{"id":"1782","channel":"Almaty TV","link":"https://live-almatytv.cdnvideo.ru/almatytv/almatytv.sdp/chunklist.m3u8?checkedby:iptvcat.com","country":"kazakhstan","liveliness":"99","status":"online","lastChecked":"2021-01-28T00:00:00Z","format":"hd","mbps":"5020","URI":["kazakhstan","kazakhstan_"]},{"id":"1781","channel":"Almaty TV, Almaty TV (KZ)","link":"http://live-almatytv.cdnvideo.ru/almatytv/almatytv.sdp/playlist.m3u8?checkedby:iptvcat.com","country":"kazakhstan","liveliness":"99","status":"online","lastChecked":"2021-01-28T00:00:00Z","format":"hd","mbps":"5020","URI":["europe","russian_federation_-_","kazakhstan","russian_federation","kazakhstan_"]},{"id":"132996","channel":"Almaty TV","link":"https://live-almatytv.cdnvideo.ru/almatytv/almatytv.sdp/playlist.m3u8?checkedby:iptvcat.com","country":"kazakhstan","liveliness":"99","status":"online","lastChecked":"2021-01-29T00:00:00Z","format":"hd","mbps":"5020","URI":["asia","kazakhstan","kazakhstan_"]},{"id":"132998","channel":"Astana TV","link":"https://sc.id-tv.kz/Astana.m3u8?checkedby:iptvcat.com","country":"kazakhstan","liveliness":"61","status":"online","lastChecked":"2021-01-29T00:00:00Z","format":"sd","mbps":"1706, ...","URI":["asia","kazakhstan","kazakhstan_"]},{"id":"13898","channel":"Astana TV, Astana TV (KZ)","link":"https://sc.id-tv.kz/Astana_38_39.m3u8?checkedby:iptvcat.com","country":"kazakhstan","liveliness":"80","status":"online","lastChecked":"2021-01-29T00:00:00Z","format":"sd","mbps":"1019","URI":["europe","russian_federation_-_","kazakhstan","russian_federation","kazakhstan_"]},{"id":"56004","channel":"Asyl Arna, KZ | Asyl Arna","link":"https://sc.id-tv.kz/AsylArna_38_39.m3u8?checkedby:iptvcat.com","country":"kazakhstan","liveliness":"93","status":"online","lastChecked":"2021-01-29T00:00:00Z","format":"sd","mbps":"1019","URI":["asia","kazakhstan","kazakhstan_"]},{"id":"132999","channel":"Atameken Business","link":"https://live-atameken.cdnvideo.ru/atameken/atameken_hq.sdp/playlist.m3u8?checkedby:iptvcat.com","country":"kazakhstan","liveliness":"96","status":"online","lastChecked":"2021-01-28T00:00:00Z","format":"hd","mbps":"3625","URI":["asia","kazakhstan","kazakhstan_"]},{"id":"1784","channel":"Atameken Business","link":"http://live-atameken.cdnvideo.ru/atameken/atameken_hq.sdp/playlist.m3u8?checkedby:iptvcat.com","country":"kazakhstan","liveliness":"97","status":"online","lastChecked":"2021-01-29T00:00:00Z","format":"hd","mbps":"3625","URI":["kazakhstan","kazakhstan_"]},{"id":"13899","channel":"Atameken Business TV","link":"https://sc.id-tv.kz/Atameken_38_39.m3u8?checkedby:iptvcat.com","country":"kazakhstan","liveliness":"92","status":"online","lastChecked":"2021-01-29T00:00:00Z","format":"sd","mbps":"1706","URI":["kazakhstan","kazakhstan_"]},{"id":"56005","channel":"Dombyra TV, KZ | Dombyra TV","link":"https://sc.id-tv.kz/Dombyra_38_39.m3u8?checkedby:iptvcat.com","country":"kazakhstan","liveliness":"84","status":"online","lastChecked":"2021-01-29T00:00:00Z","format":"sd","mbps":"2334","URI":["asia","kazakhstan","kazakhstan_"]},{"id":"133002","channel":"ID Fashion (KZ)","link":"https://sc.id-tv.kz/IDFashion.m3u8?checkedby:iptvcat.com","country":"kazakhstan","liveliness":"74","status":"online","lastChecked":"2021-01-29T00:00:00Z","format":"sd","mbps":"1706, ...","URI":["asia","kazakhstan","kazakhstan_"]},{"id":"56014","channel":"KZ | MTRK, MTRK","link":"https://tvcdn01.oktv.kz/tv/mtrk/tracks-v1a1/mono.m3u8?checkedby:iptvcat.com","country":"kazakhstan","liveliness":"98","status":"online","lastChecked":"2021-01-28T00:00:00Z","format":"sd","mbps":"1509","URI":["asia","kazakhstan","kazakhstan_"]},{"id":"56002","channel":"KZ | Мir +3, Мir +3","link":"https://sc.id-tv.kz/Mir_38_39.m3u8?checkedby:iptvcat.com","country":"kazakhstan","liveliness":"87","status":"online","lastChecked":"2021-01-29T00:00:00Z","format":"sd","mbps":"1706","URI":["asia","kazakhstan","kazakhstan_"]},{"id":"13901","channel":"Ел Арна","link":"https://sc.id-tv.kz/ElArna_38_39.m3u8?checkedby:iptvcat.com","country":"kazakhstan","liveliness":"88","status":"online","lastChecked":"2021-01-28T00:00:00Z","format":"sd","mbps":"1019","URI":["kazakhstan","kazakhstan_"]},{"id":"13903","channel":"Новое ТВ, Новое ТВ (KZ)","link":"https://sc.id-tv.kz/New_Television_38_39.m3u8?checkedby:iptvcat.com","country":"kazakhstan","liveliness":"96","status":"online","lastChecked":"2021-01-29T00:00:00Z","format":"sd","mbps":"753","URI":["kazakhstan","kazakhstan_"]},{"id":"1796","channel":"Новое телевидение","link":"http://serv25.vintera.tv:8081/novoetv/nov_tv/playlist.m3u8?checkedby:iptvcat.com","country":"kazakhstan","liveliness":"99","status":"online","lastChecked":"2021-01-30T00:00:00Z","format":"sd","mbps":"3262","URI":["kazakhstan","kazakhstan_"]},{"id":"13904","channel":"СТВ Казахстан","link":"https://sc.id-tv.kz/STV_38_39.m3u8?checkedby:iptvcat.com","country":"kazakhstan","liveliness":"85","status":"online","lastChecked":"2021-01-29T00:00:00Z","format":"sd","mbps":"1509","URI":["kazakhstan","kazakhstan_"]},{"id":"133009","channel":"СТВ Казахстан","link":"https://sc.id-tv.kz/STV.m3u8?checkedby:iptvcat.com","country":"kazakhstan","liveliness":"70","status":"online","lastChecked":"2021-01-28T00:00:00Z","format":"sd","mbps":"1509, ...","URI":["asia","kazakhstan","kazakhstan_"]},{"id":"133011","channel":"Хабар 24","link":"https://live-24kz.cdnvideo.ru/24kz/24kz.sdp/playlist.m3u8?checkedby:iptvcat.com","country":"kazakhstan","liveliness":"93","status":"online","lastChecked":"2021-01-29T00:00:00Z","format":"fhd 2k","mbps":"8378","URI":["asia","kazakhstan","kazakhstan_"]},{"id":"1781","channel":"Almaty TV, Almaty TV (KZ)","link":"http://live-almatytv.cdnvideo.ru/almatytv/almatytv.sdp/playlist.m3u8?checkedby:iptvcat.com","country":"kazakhstan","liveliness":"99","status":"online","lastChecked":"2021-01-28T00:00:00Z","format":"hd","mbps":"5020","URI":["europe","russian_federation_-_","kazakhstan","russian_federation","kazakhstan_"]},{"id":"13898","channel":"Astana TV, Astana TV (KZ)","link":"https://sc.id-tv.kz/Astana_38_39.m3u8?checkedby:iptvcat.com","country":"kazakhstan","liveliness":"80","status":"online","lastChecked":"2021-01-29T00:00:00Z","format":"sd","mbps":"1019","URI":["europe","russian_federation_-_","kazakhstan","russian_federation","kazakhstan_"]},{"id":"1781","channel":"Almaty TV, Almaty TV (KZ)","link":"http://live-almatytv.cdnvideo.ru/almatytv/almatytv.sdp/playlist.m3u8?checkedby:iptvcat.com","country":"kazakhstan","liveliness":"99","status":"online","lastChecked":"2021-01-28T00:00:00Z","format":"hd","mbps":"5020","URI":["europe","russian_federation_-_","kazakhstan","russian_federation","kazakhstan_"]},{"id":"13898","channel":"Astana TV, Astana TV (KZ)","link":"https://sc.id-tv.kz/Astana_38_39.m3u8?checkedby:iptvcat.com","country":"kazakhstan","liveliness":"80","status":"online","lastChecked":"2021-01-29T00:00:00Z","format":"sd","mbps":"1019","URI":["europe","russian_federation_-_","kazakhstan","russian_federation","kazakhstan_"]},{"id":"1781","channel":"Almaty TV, Almaty TV (KZ)","link":"http://live-almatytv.cdnvideo.ru/almatytv/almatytv.sdp/playlist.m3u8?checkedby:iptvcat.com","country":"kazakhstan","liveliness":"99","status":"online","lastChecked":"2021-01-28T00:00:00Z","format":"hd","mbps":"5020","URI":["europe","russian_federation_-_","kazakhstan","russian_federation","kazakhstan_"]},{"id":"13898","channel":"Astana TV, Astana TV (KZ)","link":"https://sc.id-tv.kz/Astana_38_39.m3u8?checkedby:iptvcat.com","country":"kazakhstan","liveliness":"80","status":"online","lastChecked":"2021-01-29T00:00:00Z","format":"sd","mbps":"1019","URI":["europe","russian_federation_-_","kazakhstan","russian_federation","kazakhstan_"]},{"id":"56000","channel":"1 Kanal Evraziya, KZ | 1 Kanal Evraziya","link":"https://sc.id-tv.kz/1KanalEvraziya_38_39.m3u8?checkedby:iptvcat.com","country":"kazakhstan","liveliness":"81","status":"online","lastChecked":"2021-01-28T00:00:00Z","format":"sd","mbps":"1019","URI":["asia","kazakhstan","kazakhstan_"]},{"id":"13896","channel":"31 канал","link":"https://sc.id-tv.kz/31Kanal_38_39.m3u8?checkedby:iptvcat.com","country":"kazakhstan","liveliness":"84","status":"online","lastChecked":"2021-01-29T00:00:00Z","format":"sd","mbps":"1706","URI":["kazakhstan","kazakhstan_"]},{"id":"13897","channel":"7 канал (KZ)","link":"https://sc.id-tv.kz/7_kanal_38_39.m3u8?checkedby:iptvcat.com","country":"kazakhstan","liveliness":"86","status":"online","lastChecked":"2021-01-29T00:00:00Z","format":"sd","mbps":"1019","URI":["kazakhstan","kazakhstan_"]},{"id":"132996","channel":"Almaty TV","link":"https://live-almatytv.cdnvideo.ru/almatytv/almatytv.sdp/playlist.m3u8?checkedby:iptvcat.com","country":"kazakhstan","liveliness":"99","status":"online","lastChecked":"2021-01-29T00:00:00Z","format":"hd","mbps":"5020","URI":["asia","kazakhstan","kazakhstan_"]},{"id":"1782","channel":"Almaty TV","link":"https://live-almatytv.cdnvideo.ru/almatytv/almatytv.sdp/chunklist.m3u8?checkedby:iptvcat.com","country":"kazakhstan","liveliness":"99","status":"online","lastChecked":"2021-01-28T00:00:00Z","format":"hd","mbps":"5020","URI":["kazakhstan","kazakhstan_"]},{"id":"1781","channel":"Almaty TV, Almaty TV (KZ)","link":"http://live-almatytv.cdnvideo.ru/almatytv/almatytv.sdp/playlist.m3u8?checkedby:iptvcat.com","country":"kazakhstan","liveliness":"99","status":"online","lastChecked":"2021-01-28T00:00:00Z","format":"hd","mbps":"5020","URI":["europe","russian_federation_-_","kazakhstan","russian_federation","kazakhstan_"]},{"id":"132998","channel":"Astana TV","link":"https://sc.id-tv.kz/Astana.m3u8?checkedby:iptvcat.com","country":"kazakhstan","liveliness":"61","status":"online","lastChecked":"2021-01-29T00:00:00Z","format":"sd","mbps":"1706, ...","URI":["asia","kazakhstan","kazakhstan_"]},{"id":"13898","channel":"Astana TV, Astana TV (KZ)","link":"https://sc.id-tv.kz/Astana_38_39.m3u8?checkedby:iptvcat.com","country":"kazakhstan","liveliness":"80","status":"online","lastChecked":"2021-01-29T00:00:00Z","format":"sd","mbps":"1019","URI":["europe","russian_federation_-_","kazakhstan","russian_federation","kazakhstan_"]},{"id":"56004","channel":"Asyl Arna, KZ | Asyl Arna","link":"https://sc.id-tv.kz/AsylArna_38_39.m3u8?checkedby:iptvcat.com","country":"kazakhstan","liveliness":"93","status":"online","lastChecked":"2021-01-29T00:00:00Z","format":"sd","mbps":"1019","URI":["asia","kazakhstan","kazakhstan_"]},{"id":"132999","channel":"Atameken Business","link":"https://live-atameken.cdnvideo.ru/atameken/atameken_hq.sdp/playlist.m3u8?checkedby:iptvcat.com","country":"kazakhstan","liveliness":"96","status":"online","lastChecked":"2021-01-28T00:00:00Z","format":"hd","mbps":"3625","URI":["asia","kazakhstan","kazakhstan_"]},{"id":"1784","channel":"Atameken Business","link":"http://live-atameken.cdnvideo.ru/atameken/atameken_hq.sdp/playlist.m3u8?checkedby:iptvcat.com","country":"kazakhstan","liveliness":"97","status":"online","lastChecked":"2021-01-29T00:00:00Z","format":"hd","mbps":"3625","URI":["kazakhstan","kazakhstan_"]},{"id":"13899","channel":"Atameken Business TV","link":"https://sc.id-tv.kz/Atameken_38_39.m3u8?checkedby:iptvcat.com","country":"kazakhstan","liveliness":"92","status":"online","lastChecked":"2021-01-29T00:00:00Z","format":"sd","mbps":"1706","URI":["kazakhstan","kazakhstan_"]},{"id":"56005","channel":"Dombyra TV, KZ | Dombyra TV","link":"https://sc.id-tv.kz/Dombyra_38_39.m3u8?checkedby:iptvcat.com","country":"kazakhstan","liveliness":"84","status":"online","lastChecked":"2021-01-29T00:00:00Z","format":"sd","mbps":"2334","URI":["asia","kazakhstan","kazakhstan_"]},{"id":"133002","channel":"ID Fashion (KZ)","link":"https://sc.id-tv.kz/IDFashion.m3u8?checkedby:iptvcat.com","country":"kazakhstan","liveliness":"74","status":"online","lastChecked":"2021-01-29T00:00:00Z","format":"sd","mbps":"1706, ...","URI":["asia","kazakhstan","kazakhstan_"]},{"id":"56014","channel":"KZ | MTRK, MTRK","link":"https://tvcdn01.oktv.kz/tv/mtrk/tracks-v1a1/mono.m3u8?checkedby:iptvcat.com","country":"kazakhstan","liveliness":"98","status":"online","lastChecked":"2021-01-28T00:00:00Z","format":"sd","mbps":"1509","URI":["asia","kazakhstan","kazakhstan_"]},{"id":"56002","channel":"KZ | Мir +3, Мir +3","link":"https://sc.id-tv.kz/Mir_38_39.m3u8?checkedby:iptvcat.com","country":"kazakhstan","liveliness":"87","status":"online","lastChecked":"2021-01-29T00:00:00Z","format":"sd","mbps":"1706","URI":["asia","kazakhstan","kazakhstan_"]},{"id":"13901","channel":"Ел Арна","link":"https://sc.id-tv.kz/ElArna_38_39.m3u8?checkedby:iptvcat.com","country":"kazakhstan","liveliness":"88","status":"online","lastChecked":"2021-01-28T00:00:00Z","format":"sd","mbps":"1019","URI":["kazakhstan","kazakhstan_"]},{"id":"13903","channel":"Новое ТВ, Новое ТВ (KZ)","link":"https://sc.id-tv.kz/New_Television_38_39.m3u8?checkedby:iptvcat.com","country":"kazakhstan","liveliness":"96","status":"online","lastChecked":"2021-01-29T00:00:00Z","format":"sd","mbps":"753","URI":["kazakhstan","kazakhstan_"]},{"id":"1796","channel":"Новое телевидение","link":"http://serv25.vintera.tv:8081/novoetv/nov_tv/playlist.m3u8?checkedby:iptvcat.com","country":"kazakhstan","liveliness":"99","status":"online","lastChecked":"2021-01-30T00:00:00Z","format":"sd","mbps":"3262","URI":["kazakhstan","kazakhstan_"]},{"id":"13904","channel":"СТВ Казахстан","link":"https://sc.id-tv.kz/STV_38_39.m3u8?checkedby:iptvcat.com","country":"kazakhstan","liveliness":"85","status":"online","lastChecked":"2021-01-29T00:00:00Z","format":"sd","mbps":"1509","URI":["kazakhstan","kazakhstan_"]},{"id":"133009","channel":"СТВ Казахстан","link":"https://sc.id-tv.kz/STV.m3u8?checkedby:iptvcat.com","country":"kazakhstan","liveliness":"70","status":"online","lastChecked":"2021-01-28T00:00:00Z","format":"sd","mbps":"1509, ...","URI":["asia","kazakhstan","kazakhstan_"]},{"id":"133011","channel":"Хабар 24","link":"https://live-24kz.cdnvideo.ru/24kz/24kz.sdp/playlist.m3u8?checkedby:iptvcat.com","country":"kazakhstan","liveliness":"93","status":"online","lastChecked":"2021-01-29T00:00:00Z","format":"fhd 2k","mbps":"8378","URI":["asia","kazakhstan","kazakhstan_"]},{"id":"1781","channel":"Almaty TV, Almaty TV (KZ)","link":"http://live-almatytv.cdnvideo.ru/almatytv/almatytv.sdp/playlist.m3u8?checkedby:iptvcat.com","country":"kazakhstan","liveliness":"99","status":"online","lastChecked":"2021-01-28T00:00:00Z","format":"hd","mbps":"5020","URI":["europe","russian_federation_-_","kazakhstan","russian_federation","kazakhstan_"]},{"id":"13898","channel":"Astana TV, Astana TV (KZ)","link":"https://sc.id-tv.kz/Astana_38_39.m3u8?checkedby:iptvcat.com","country":"kazakhstan","liveliness":"80","status":"online","lastChecked":"2021-01-29T00:00:00Z","format":"sd","mbps":"1019","URI":["europe","russian_federation_-_","kazakhstan","russian_federation","kazakhstan_"]},{"id":"1781","channel":"Almaty TV, Almaty TV (KZ)","link":"http://live-almatytv.cdnvideo.ru/almatytv/almatytv.sdp/playlist.m3u8?checkedby:iptvcat.com","country":"kazakhstan","liveliness":"99","status":"online","lastChecked":"2021-01-28T00:00:00Z","format":"hd","mbps":"5020","URI":["europe","russian_federation_-_","kazakhstan","russian_federation","kazakhstan_"]},{"id":"13898","channel":"Astana TV, Astana TV (KZ)","link":"https://sc.id-tv.kz/Astana_38_39.m3u8?checkedby:iptvcat.com","country":"kazakhstan","liveliness":"80","status":"online","lastChecked":"2021-01-29T00:00:00Z","format":"sd","mbps":"1019","URI":["europe","russian_federation_-_","kazakhstan","russian_federation","kazakhstan_"]},{"id":"1781","channel":"Almaty TV, Almaty TV (KZ)","link":"http://live-almatytv.cdnvideo.ru/almatytv/almatytv.sdp/playlist.m3u8?checkedby:iptvcat.com","country":"kazakhstan","liveliness":"99","status":"online","lastChecked":"2021-01-28T00:00:00Z","format":"hd","mbps":"5020","URI":["europe","russian_federation_-_","kazakhstan","russian_federation","kazakhstan_"]},{"id":"13898","channel":"Astana TV, Astana TV (KZ)","link":"https://sc.id-tv.kz/Astana_38_39.m3u8?checkedby:iptvcat.com","country":"kazakhstan","liveliness":"80","status":"online","lastChecked":"2021-01-29T00:00:00Z","format":"sd","mbps":"1019","URI":["europe","russian_federation_-_","kazakhstan","russian_federation","kazakhstan_"]}]