[{"id":"850034","channel":"Doma TV","link":"http://sara12.webhop.net:8000/live/emad_854959/k3aRL3Eb/58188.m3u8?checkedby:iptvcat.com","country":"serbia","liveliness":"33","status":"offline","lastChecked":"2021-01-30T00:00:00Z","format":"sd","mbps":"2883","URI":["serbia_-","ex_yugoslavia_-","europe"]},{"id":"850033","channel":"Mini TV","link":"http://sara12.webhop.net:8000/live/emad_854959/k3aRL3Eb/58187.m3u8?checkedby:iptvcat.com","country":"serbia","liveliness":"67","status":"online","lastChecked":"2021-01-30T00:00:00Z","format":"sd","mbps":"2883","URI":["serbia_-","ex_yugoslavia","europe","new_channels"]},{"id":"850032","channel":"Pink Folk 2","link":"http://sara12.webhop.net:8000/live/emad_854959/k3aRL3Eb/58186.m3u8?checkedby:iptvcat.com","country":"serbia","liveliness":"100","status":"online","lastChecked":"2021-01-29T00:00:00Z","format":"sd","mbps":"4532","URI":["serbia_-","ex_yugoslavia","europe","new_channels"]},{"id":"850040","channel":"RTL","link":"http://sara12.webhop.net:8000/live/emad_854959/k3aRL3Eb/58194.m3u8?checkedby:iptvcat.com","country":"serbia","liveliness":"100","status":"online","lastChecked":"2021-01-29T00:00:00Z","format":"fhd 2k","mbps":"13873","URI":["serbia_-","ex_yugoslavia","europe","new_channels"]},{"id":"850041","channel":"RTL 2","link":"http://sara12.webhop.net:8000/live/emad_854959/k3aRL3Eb/58195.m3u8?checkedby:iptvcat.com","country":"serbia","liveliness":"100","status":"online","lastChecked":"2021-01-29T00:00:00Z","format":"sd","mbps":"2883","URI":["serbia_-","ex_yugoslavia","europe","new_channels"]},{"id":"850036","channel":"RTL Crime","link":"http://sara12.webhop.net:8000/live/emad_854959/k3aRL3Eb/58190.m3u8?checkedby:iptvcat.com","country":"serbia","liveliness":"67","status":"online","lastChecked":"2021-01-30T00:00:00Z","format":"sd","mbps":"2883","URI":["serbia_-","ex_yugoslavia","europe","new_channels"]},{"id":"850037","channel":"RTL Kockica","link":"http://sara12.webhop.net:8000/live/emad_854959/k3aRL3Eb/58191.m3u8?checkedby:iptvcat.com","country":"serbia","liveliness":"67","status":"online","lastChecked":"2021-01-30T00:00:00Z","format":"sd","mbps":"2883","URI":["serbia_-","ex_yugoslavia","europe","new_channels"]},{"id":"850038","channel":"RTL Living","link":"http://sara12.webhop.net:8000/live/emad_854959/k3aRL3Eb/58192.m3u8?checkedby:iptvcat.com","country":"serbia","liveliness":"33","status":"offline","lastChecked":"2021-01-30T00:00:00Z","format":"sd","mbps":"2883","URI":["serbia_-","ex_yugoslavia","europe"]},{"id":"850039","channel":"RTL Passion","link":"http://sara12.webhop.net:8000/live/emad_854959/k3aRL3Eb/58193.m3u8?checkedby:iptvcat.com","country":"serbia","liveliness":"100","status":"online","lastChecked":"2021-01-29T00:00:00Z","format":"sd","mbps":"2883","URI":["serbia_-","ex_yugoslavia","europe","new_channels"]},{"id":"850042","channel":"RTS 1","link":"http://sara12.webhop.net:8000/live/emad_854959/k3aRL3Eb/58196.m3u8?checkedby:iptvcat.com","country":"serbia","liveliness":"100","status":"online","lastChecked":"2021-01-29T00:00:00Z","format":"sd","mbps":"2883","URI":["serbia_-","ex_yugoslavia","europe","new_channels"]},{"id":"850043","channel":"RTS 2","link":"http://sara12.webhop.net:8000/live/emad_854959/k3aRL3Eb/58197.m3u8?checkedby:iptvcat.com","country":"serbia","liveliness":"67","status":"online","lastChecked":"2021-01-30T00:00:00Z","format":"sd","mbps":"2883","URI":["serbia_-","ex_yugoslavia","europe","new_channels"]},{"id":"850035","channel":"RTV Novi Pazar","link":"http://sara12.webhop.net:8000/live/emad_854959/k3aRL3Eb/58189.m3u8?checkedby:iptvcat.com","country":"serbia","liveliness":"100","status":"online","lastChecked":"2021-01-29T00:00:00Z","format":"sd","mbps":"2334","URI":["serbia_-","ex_yugoslavia","europe","new_channels"]},{"id":"850029","channel":"RTV1","link":"http://sara12.webhop.net:8000/live/emad_854959/k3aRL3Eb/58177.m3u8?checkedby:iptvcat.com","country":"serbia","liveliness":"100","status":"online","lastChecked":"2021-01-29T00:00:00Z","format":"sd","mbps":"2883","URI":["serbia_-","ex_yugoslavia","europe","new_channels"]},{"id":"850030","channel":"RTV2","link":"http://sara12.webhop.net:8000/live/emad_854959/k3aRL3Eb/58178.m3u8?checkedby:iptvcat.com","country":"serbia","liveliness":"33","status":"offline","lastChecked":"2021-01-30T00:00:00Z","format":"sd","mbps":"2883","URI":["serbia_-","ex_yugoslavia","europe"]},{"id":"850031","channel":"SportKlub Golf","link":"http://sara12.webhop.net:8000/live/emad_854959/k3aRL3Eb/58182.m3u8?checkedby:iptvcat.com","country":"serbia","liveliness":"33","status":"offline","lastChecked":"2021-01-30T00:00:00Z","format":"sd","mbps":"2883","URI":["serbia_-","ex_yugoslavia","europe","sport"]},{"id":"62390","channel":"TV Duga +  rtm","link":"rtmp://w10.streamgb.com/dugaplus/dugaplus?checkedby:iptvcat.com","country":"serbia","liveliness":"87","status":"online","lastChecked":"2021-01-29T00:00:00Z","format":"sd","mbps":"1688","URI":["serbia_-","ex_yugoslavia","europe"]},{"id":"2506","channel":"TV Duga Plus","link":"http://w10.streamgb.com:1935/dugaplus/dugaplus/playlist.m3u8?checkedby:iptvcat.com","country":"serbia","liveliness":"90","status":"online","lastChecked":"2021-01-29T00:00:00Z","format":"sd","mbps":"1688","URI":["serbia_-"]},{"id":"62391","channel":"TV Hram  rtm","link":"rtmp://178.253.194.75/live/hram.stream?checkedby:iptvcat.com","country":"serbia","liveliness":"96","status":"online","lastChecked":"2021-01-29T00:00:00Z","format":"sd","mbps":"1509","URI":["serbia_-","ex_yugoslavia","europe"]},{"id":"2505","channel":"Televizija Leskovac","link":"http://best.str.nettvplus.com:8080/stream/?channel=tvleskovac\u0026stream=1mb\u0026sp=nettvplus?u=X0B2YB95\u0026checkedby:iptvcat.com","country":"serbia","liveliness":"98","status":"online","lastChecked":"2021-01-29T00:00:00Z","format":"sd","mbps":"3262","URI":["serbia_-"]},{"id":"850031","channel":"SportKlub Golf","link":"http://sara12.webhop.net:8000/live/emad_854959/k3aRL3Eb/58182.m3u8?checkedby:iptvcat.com","country":"serbia","liveliness":"33","status":"offline","lastChecked":"2021-01-30T00:00:00Z","format":"sd","mbps":"2883","URI":["serbia_-","ex_yugoslavia","europe","sport"]},{"id":"62390","channel":"TV Duga +  rtm","link":"rtmp://w10.streamgb.com/dugaplus/dugaplus?checkedby:iptvcat.com","country":"serbia","liveliness":"87","status":"online","lastChecked":"2021-01-29T00:00:00Z","format":"sd","mbps":"1688","URI":["serbia_-","ex_yugoslavia","europe"]},{"id":"62391","channel":"TV Hram  rtm","link":"rtmp://178.253.194.75/live/hram.stream?checkedby:iptvcat.com","country":"serbia","liveliness":"96","status":"online","lastChecked":"2021-01-29T00:00:00Z","format":"sd","mbps":"1509","URI":["serbia_-","ex_yugoslavia","europe"]},{"id":"850040","channel":"RTL","link":"http://sara12.webhop.net:8000/live/emad_854959/k3aRL3Eb/58194.m3u8?checkedby:iptvcat.com","country":"serbia","liveliness":"100","status":"online","lastChecked":"2021-01-29T00:00:00Z","format":"fhd 2k","mbps":"13873","URI":["serbia_-","ex_yugoslavia","europe","new_channels"]},{"id":"850041","channel":"RTL 2","link":"http://sara12.webhop.net:8000/live/emad_854959/k3aRL3Eb/58195.m3u8?checkedby:iptvcat.com","country":"serbia","liveliness":"100","status":"online","lastChecked":"2021-01-29T00:00:00Z","format":"sd","mbps":"2883","URI":["serbia_-","ex_yugoslavia","europe","new_channels"]},{"id":"850036","channel":"RTL Crime","link":"http://sara12.webhop.net:8000/live/emad_854959/k3aRL3Eb/58190.m3u8?checkedby:iptvcat.com","country":"serbia","liveliness":"67","status":"online","lastChecked":"2021-01-30T00:00:00Z","format":"sd","mbps":"2883","URI":["serbia_-","ex_yugoslavia","europe","new_channels"]},{"id":"850037","channel":"RTL Kockica","link":"http://sara12.webhop.net:8000/live/emad_854959/k3aRL3Eb/58191.m3u8?checkedby:iptvcat.com","country":"serbia","liveliness":"67","status":"online","lastChecked":"2021-01-30T00:00:00Z","format":"sd","mbps":"2883","URI":["serbia_-","ex_yugoslavia","europe","new_channels"]},{"id":"850038","channel":"RTL Living","link":"http://sara12.webhop.net:8000/live/emad_854959/k3aRL3Eb/58192.m3u8?checkedby:iptvcat.com","country":"serbia","liveliness":"33","status":"offline","lastChecked":"2021-01-30T00:00:00Z","format":"sd","mbps":"2883","URI":["serbia_-","ex_yugoslavia","europe"]},{"id":"850039","channel":"RTL Passion","link":"http://sara12.webhop.net:8000/live/emad_854959/k3aRL3Eb/58193.m3u8?checkedby:iptvcat.com","country":"serbia","liveliness":"100","status":"online","lastChecked":"2021-01-29T00:00:00Z","format":"sd","mbps":"2883","URI":["serbia_-","ex_yugoslavia","europe","new_channels"]},{"id":"850042","channel":"RTS 1","link":"http://sara12.webhop.net:8000/live/emad_854959/k3aRL3Eb/58196.m3u8?checkedby:iptvcat.com","country":"serbia","liveliness":"100","status":"online","lastChecked":"2021-01-29T00:00:00Z","format":"sd","mbps":"2883","URI":["serbia_-","ex_yugoslavia","europe","new_channels"]},{"id":"850043","channel":"RTS 2","link":"http://sara12.webhop.net:8000/live/emad_854959/k3aRL3Eb/58197.m3u8?checkedby:iptvcat.com","country":"serbia","liveliness":"67","status":"online","lastChecked":"2021-01-30T00:00:00Z","format":"sd","mbps":"2883","URI":["serbia_-","ex_yugoslavia","europe","new_channels"]},{"id":"850035","channel":"RTV Novi Pazar","link":"http://sara12.webhop.net:8000/live/emad_854959/k3aRL3Eb/58189.m3u8?checkedby:iptvcat.com","country":"serbia","liveliness":"100","status":"online","lastChecked":"2021-01-29T00:00:00Z","format":"sd","mbps":"2334","URI":["serbia_-","ex_yugoslavia","europe","new_channels"]},{"id":"850029","channel":"RTV1","link":"http://sara12.webhop.net:8000/live/emad_854959/k3aRL3Eb/58177.m3u8?checkedby:iptvcat.com","country":"serbia","liveliness":"100","status":"online","lastChecked":"2021-01-29T00:00:00Z","format":"sd","mbps":"2883","URI":["serbia_-","ex_yugoslavia","europe","new_channels"]},{"id":"850030","channel":"RTV2","link":"http://sara12.webhop.net:8000/live/emad_854959/k3aRL3Eb/58178.m3u8?checkedby:iptvcat.com","country":"serbia","liveliness":"33","status":"offline","lastChecked":"2021-01-30T00:00:00Z","format":"sd","mbps":"2883","URI":["serbia_-","ex_yugoslavia","europe"]},{"id":"850032","channel":"Pink Folk 2","link":"http://sara12.webhop.net:8000/live/emad_854959/k3aRL3Eb/58186.m3u8?checkedby:iptvcat.com","country":"serbia","liveliness":"100","status":"online","lastChecked":"2021-01-29T00:00:00Z","format":"sd","mbps":"4532","URI":["serbia_-","ex_yugoslavia","europe","new_channels"]},{"id":"850033","channel":"Mini TV","link":"http://sara12.webhop.net:8000/live/emad_854959/k3aRL3Eb/58187.m3u8?checkedby:iptvcat.com","country":"serbia","liveliness":"67","status":"online","lastChecked":"2021-01-30T00:00:00Z","format":"sd","mbps":"2883","URI":["serbia_-","ex_yugoslavia","europe","new_channels"]},{"id":"850033","channel":"Mini TV","link":"http://sara12.webhop.net:8000/live/emad_854959/k3aRL3Eb/58187.m3u8?checkedby:iptvcat.com","country":"serbia","liveliness":"67","status":"online","lastChecked":"2021-01-30T00:00:00Z","format":"sd","mbps":"2883","URI":["serbia_-","ex_yugoslavia","europe","new_channels"]},{"id":"850032","channel":"Pink Folk 2","link":"http://sara12.webhop.net:8000/live/emad_854959/k3aRL3Eb/58186.m3u8?checkedby:iptvcat.com","country":"serbia","liveliness":"100","status":"online","lastChecked":"2021-01-29T00:00:00Z","format":"sd","mbps":"4532","URI":["serbia_-","ex_yugoslavia","europe","new_channels"]},{"id":"850034","channel":"Doma TV","link":"http://sara12.webhop.net:8000/live/emad_854959/k3aRL3Eb/58188.m3u8?checkedby:iptvcat.com","country":"serbia","liveliness":"33","status":"offline","lastChecked":"2021-01-30T00:00:00Z","format":"sd","mbps":"2883","URI":["serbia_-","ex_yugoslavia_-","europe"]},{"id":"850034","channel":"Doma TV","link":"http://sara12.webhop.net:8000/live/emad_854959/k3aRL3Eb/58188.m3u8?checkedby:iptvcat.com","country":"serbia","liveliness":"33","status":"offline","lastChecked":"2021-01-30T00:00:00Z","format":"sd","mbps":"2883","URI":["serbia_-","ex_yugoslavia_-","europe"]},{"id":"850034","channel":"Doma TV","link":"http://sara12.webhop.net:8000/live/emad_854959/k3aRL3Eb/58188.m3u8?checkedby:iptvcat.com","country":"serbia","liveliness":"33","status":"offline","lastChecked":"2021-01-30T00:00:00Z","format":"sd","mbps":"2883","URI":["serbia_-","ex_yugoslavia_-","europe"]},{"id":"850033","channel":"Mini TV","link":"http://sara12.webhop.net:8000/live/emad_854959/k3aRL3Eb/58187.m3u8?checkedby:iptvcat.com","country":"serbia","liveliness":"67","status":"online","lastChecked":"2021-01-30T00:00:00Z","format":"sd","mbps":"2883","URI":["serbia_-","ex_yugoslavia","europe","new_channels"]},{"id":"850032","channel":"Pink Folk 2","link":"http://sara12.webhop.net:8000/live/emad_854959/k3aRL3Eb/58186.m3u8?checkedby:iptvcat.com","country":"serbia","liveliness":"100","status":"online","lastChecked":"2021-01-29T00:00:00Z","format":"sd","mbps":"4532","URI":["serbia_-","ex_yugoslavia","europe","new_channels"]},{"id":"850040","channel":"RTL","link":"http://sara12.webhop.net:8000/live/emad_854959/k3aRL3Eb/58194.m3u8?checkedby:iptvcat.com","country":"serbia","liveliness":"100","status":"online","lastChecked":"2021-01-29T00:00:00Z","format":"fhd 2k","mbps":"13873","URI":["serbia_-","ex_yugoslavia","europe","new_channels"]},{"id":"850041","channel":"RTL 2","link":"http://sara12.webhop.net:8000/live/emad_854959/k3aRL3Eb/58195.m3u8?checkedby:iptvcat.com","country":"serbia","liveliness":"100","status":"online","lastChecked":"2021-01-29T00:00:00Z","format":"sd","mbps":"2883","URI":["serbia_-","ex_yugoslavia","europe","new_channels"]},{"id":"850036","channel":"RTL Crime","link":"http://sara12.webhop.net:8000/live/emad_854959/k3aRL3Eb/58190.m3u8?checkedby:iptvcat.com","country":"serbia","liveliness":"67","status":"online","lastChecked":"2021-01-30T00:00:00Z","format":"sd","mbps":"2883","URI":["serbia_-","ex_yugoslavia","europe","new_channels"]},{"id":"850037","channel":"RTL Kockica","link":"http://sara12.webhop.net:8000/live/emad_854959/k3aRL3Eb/58191.m3u8?checkedby:iptvcat.com","country":"serbia","liveliness":"67","status":"online","lastChecked":"2021-01-30T00:00:00Z","format":"sd","mbps":"2883","URI":["serbia_-","ex_yugoslavia","europe","new_channels"]},{"id":"850038","channel":"RTL Living","link":"http://sara12.webhop.net:8000/live/emad_854959/k3aRL3Eb/58192.m3u8?checkedby:iptvcat.com","country":"serbia","liveliness":"33","status":"offline","lastChecked":"2021-01-30T00:00:00Z","format":"sd","mbps":"2883","URI":["serbia_-","ex_yugoslavia","europe"]},{"id":"850039","channel":"RTL Passion","link":"http://sara12.webhop.net:8000/live/emad_854959/k3aRL3Eb/58193.m3u8?checkedby:iptvcat.com","country":"serbia","liveliness":"100","status":"online","lastChecked":"2021-01-29T00:00:00Z","format":"sd","mbps":"2883","URI":["serbia_-","ex_yugoslavia","europe","new_channels"]},{"id":"850042","channel":"RTS 1","link":"http://sara12.webhop.net:8000/live/emad_854959/k3aRL3Eb/58196.m3u8?checkedby:iptvcat.com","country":"serbia","liveliness":"100","status":"online","lastChecked":"2021-01-29T00:00:00Z","format":"sd","mbps":"2883","URI":["serbia_-","ex_yugoslavia","europe","new_channels"]},{"id":"850043","channel":"RTS 2","link":"http://sara12.webhop.net:8000/live/emad_854959/k3aRL3Eb/58197.m3u8?checkedby:iptvcat.com","country":"serbia","liveliness":"67","status":"online","lastChecked":"2021-01-30T00:00:00Z","format":"sd","mbps":"2883","URI":["serbia_-","ex_yugoslavia","europe","new_channels"]},{"id":"850035","channel":"RTV Novi Pazar","link":"http://sara12.webhop.net:8000/live/emad_854959/k3aRL3Eb/58189.m3u8?checkedby:iptvcat.com","country":"serbia","liveliness":"100","status":"online","lastChecked":"2021-01-29T00:00:00Z","format":"sd","mbps":"2334","URI":["serbia_-","ex_yugoslavia","europe","new_channels"]},{"id":"850029","channel":"RTV1","link":"http://sara12.webhop.net:8000/live/emad_854959/k3aRL3Eb/58177.m3u8?checkedby:iptvcat.com","country":"serbia","liveliness":"100","status":"online","lastChecked":"2021-01-29T00:00:00Z","format":"sd","mbps":"2883","URI":["serbia_-","ex_yugoslavia","europe","new_channels"]},{"id":"850030","channel":"RTV2","link":"http://sara12.webhop.net:8000/live/emad_854959/k3aRL3Eb/58178.m3u8?checkedby:iptvcat.com","country":"serbia","liveliness":"33","status":"offline","lastChecked":"2021-01-30T00:00:00Z","format":"sd","mbps":"2883","URI":["serbia_-","ex_yugoslavia","europe"]},{"id":"850031","channel":"SportKlub Golf","link":"http://sara12.webhop.net:8000/live/emad_854959/k3aRL3Eb/58182.m3u8?checkedby:iptvcat.com","country":"serbia","liveliness":"33","status":"offline","lastChecked":"2021-01-30T00:00:00Z","format":"sd","mbps":"2883","URI":["serbia_-","ex_yugoslavia","europe","sport"]},{"id":"62390","channel":"TV Duga +  rtm","link":"rtmp://w10.streamgb.com/dugaplus/dugaplus?checkedby:iptvcat.com","country":"serbia","liveliness":"87","status":"online","lastChecked":"2021-01-29T00:00:00Z","format":"sd","mbps":"1688","URI":["serbia_-","ex_yugoslavia","europe"]},{"id":"62391","channel":"TV Hram  rtm","link":"rtmp://178.253.194.75/live/hram.stream?checkedby:iptvcat.com","country":"serbia","liveliness":"96","status":"online","lastChecked":"2021-01-29T00:00:00Z","format":"sd","mbps":"1509","URI":["serbia_-","ex_yugoslavia","europe"]},{"id":"850031","channel":"SportKlub Golf","link":"http://sara12.webhop.net:8000/live/emad_854959/k3aRL3Eb/58182.m3u8?checkedby:iptvcat.com","country":"serbia","liveliness":"33","status":"offline","lastChecked":"2021-01-30T00:00:00Z","format":"sd","mbps":"2883","URI":["serbia_-","ex_yugoslavia","europe","sport"]},{"id":"850031","channel":"SportKlub Golf","link":"http://sara12.webhop.net:8000/live/emad_854959/k3aRL3Eb/58182.m3u8?checkedby:iptvcat.com","country":"serbia","liveliness":"33","status":"offline","lastChecked":"2021-01-30T00:00:00Z","format":"sd","mbps":"2883","URI":["serbia_-","ex_yugoslavia","europe","sport"]},{"id":"850033","channel":"Mini TV","link":"http://sara12.webhop.net:8000/live/emad_854959/k3aRL3Eb/58187.m3u8?checkedby:iptvcat.com","country":"serbia","liveliness":"67","status":"online","lastChecked":"2021-01-30T00:00:00Z","format":"sd","mbps":"2883","URI":["serbia_-","ex_yugoslavia","europe","new_channels"]},{"id":"850032","channel":"Pink Folk 2","link":"http://sara12.webhop.net:8000/live/emad_854959/k3aRL3Eb/58186.m3u8?checkedby:iptvcat.com","country":"serbia","liveliness":"100","status":"online","lastChecked":"2021-01-29T00:00:00Z","format":"sd","mbps":"4532","URI":["serbia_-","ex_yugoslavia","europe","new_channels"]},{"id":"850040","channel":"RTL","link":"http://sara12.webhop.net:8000/live/emad_854959/k3aRL3Eb/58194.m3u8?checkedby:iptvcat.com","country":"serbia","liveliness":"100","status":"online","lastChecked":"2021-01-29T00:00:00Z","format":"fhd 2k","mbps":"13873","URI":["serbia_-","ex_yugoslavia","europe","new_channels"]},{"id":"850041","channel":"RTL 2","link":"http://sara12.webhop.net:8000/live/emad_854959/k3aRL3Eb/58195.m3u8?checkedby:iptvcat.com","country":"serbia","liveliness":"100","status":"online","lastChecked":"2021-01-29T00:00:00Z","format":"sd","mbps":"2883","URI":["serbia_-","ex_yugoslavia","europe","new_channels"]},{"id":"850036","channel":"RTL Crime","link":"http://sara12.webhop.net:8000/live/emad_854959/k3aRL3Eb/58190.m3u8?checkedby:iptvcat.com","country":"serbia","liveliness":"67","status":"online","lastChecked":"2021-01-30T00:00:00Z","format":"sd","mbps":"2883","URI":["serbia_-","ex_yugoslavia","europe","new_channels"]},{"id":"850037","channel":"RTL Kockica","link":"http://sara12.webhop.net:8000/live/emad_854959/k3aRL3Eb/58191.m3u8?checkedby:iptvcat.com","country":"serbia","liveliness":"67","status":"online","lastChecked":"2021-01-30T00:00:00Z","format":"sd","mbps":"2883","URI":["serbia_-","ex_yugoslavia","europe","new_channels"]},{"id":"850039","channel":"RTL Passion","link":"http://sara12.webhop.net:8000/live/emad_854959/k3aRL3Eb/58193.m3u8?checkedby:iptvcat.com","country":"serbia","liveliness":"100","status":"online","lastChecked":"2021-01-29T00:00:00Z","format":"sd","mbps":"2883","URI":["serbia_-","ex_yugoslavia","europe","new_channels"]},{"id":"850042","channel":"RTS 1","link":"http://sara12.webhop.net:8000/live/emad_854959/k3aRL3Eb/58196.m3u8?checkedby:iptvcat.com","country":"serbia","liveliness":"100","status":"online","lastChecked":"2021-01-29T00:00:00Z","format":"sd","mbps":"2883","URI":["serbia_-","ex_yugoslavia","europe","new_channels"]},{"id":"850043","channel":"RTS 2","link":"http://sara12.webhop.net:8000/live/emad_854959/k3aRL3Eb/58197.m3u8?checkedby:iptvcat.com","country":"serbia","liveliness":"67","status":"online","lastChecked":"2021-01-30T00:00:00Z","format":"sd","mbps":"2883","URI":["serbia_-","ex_yugoslavia","europe","new_channels"]},{"id":"850035","channel":"RTV Novi Pazar","link":"http://sara12.webhop.net:8000/live/emad_854959/k3aRL3Eb/58189.m3u8?checkedby:iptvcat.com","country":"serbia","liveliness":"100","status":"online","lastChecked":"2021-01-29T00:00:00Z","format":"sd","mbps":"2334","URI":["serbia_-","ex_yugoslavia","europe","new_channels"]},{"id":"850029","channel":"RTV1","link":"http://sara12.webhop.net:8000/live/emad_854959/k3aRL3Eb/58177.m3u8?checkedby:iptvcat.com","country":"serbia","liveliness":"100","status":"online","lastChecked":"2021-01-29T00:00:00Z","format":"sd","mbps":"2883","URI":["serbia_-","ex_yugoslavia","europe","new_channels"]}]